kos_Htools/__init__.py
kos_Htools/redis_core/__init__.py
kos_Htools/redis_core/redisetup.py
kos_Htools/sql/__init__.py
kos_Htools/sql/sql_alchemy/__init__.py
kos_Htools/sql/sql_alchemy/dao.py
kos_Htools/telethon_core/__init__.py
kos_Htools/telethon_core/clients.py
kos_Htools/telethon_core/config.py
kos_Htools/telethon_core/settings.py
kos_Htools/telethon_core/utils/__init__.py
kos_Htools/telethon_core/utils/dataclasses.py
kos_Htools/telethon_core/utils/other.py
kos_Htools/telethon_core/utils/parse.py
kos_Htools/utils/__init__.py
kos_Htools/utils/time.py
kos_htools-0.1.6.4.post2.dist-info/licenses/license
kos_htools-0.1.6.4.post2.dist-info/METADATA
kos_htools-0.1.6.4.post2.dist-info/WHEEL
kos_htools-0.1.6.4.post2.dist-info/top_level.txt
kos_htools-0.1.6.4.post2.dist-info/RECORD
