Metadata-Version: 2.4
Name: kos_Htools
Version: 0.1.6.4.post2
Summary: Библиотека для работы с Telegram, Redis, SQLAlchemy
Home-page: https://github.com/KociHH/Kos_Htools-lib
Author: KociHH
Author-email: defensiv2010@gmail.com
Classifier: Programming Language :: Python :: 3
Classifier: License :: OSI Approved :: MIT License
Classifier: Operating System :: OS Independent
Requires-Python: >=3.6
License-File: license
Requires-Dist: telethon>=1.39.0
Requires-Dist: python-dotenv>=1.0.0
Requires-Dist: redis>=6.2.0
Requires-Dist: sqlalchemy>=2.0.0
Requires-Dist: pytz>=2025.1
Dynamic: author
Dynamic: author-email
Dynamic: classifier
Dynamic: description
Dynamic: description-content-type
Dynamic: home-page
Dynamic: license-file
Dynamic: requires-dist
Dynamic: requires-python
Dynamic: summary
